{
	"description": "项目配置文件",
	"packOptions": {
		"ignore": []
	},
	"setting": {
		"urlCheck": false,
		"es6": true,
		"enhance": false,
		"postcss": true,
		"preloadBackgroundData": false,
		"minified": true,
		"newFeature": false,
		"coverView": true,
		"nodeModules": false,
		"autoAudits": false,
		"showShadowRootInWxmlPanel": true,
		"scopeDataCheck": false,
		"uglifyFileName": false,
		"checkInvalidKey": true,
		"checkSiteMap": true,
		"uploadWithSourceMap": true,
		"babelSetting": {
			"ignore": [],
			"disablePlugins": [],
			"outputPath": ""
		},
		"useCompilerModule": false,
		"userConfirmedUseCompilerModuleSwitch": false,
		"compileHotReLoad": false,
		"useIsolateContext": true
	},
	"compileType": "miniprogram",
	"libVersion": "2.12.0",
	"appid": "wxa125e55c9873e031",
	"projectname": "%E7%BD%91%E6%98%93%E4%BA%91%E9%9F%B3%E4%B9%90_%E5%B0%8F%E7%A8%8B%E5%BA%8F",
	"debugOptions": {
		"hidedInDevtools": []
	},
	"scripts": {},
	"isGameTourist": false,
	"simulatorType": "wechat",
	"simulatorPluginLibVersion": {},
	"condition": {
		"search": {
			"current": -1,
			"list": []
		},
		"conversation": {
			"current": -1,
			"list": []
		},
		"game": {
			"current": -1,
			"list": []
		},
		"plugin": {
			"current": -1,
			"list": []
		},
		"gamePlugin": {
			"current": -1,
			"list": []
		},
		"miniprogram": {
			"current": -1,
			"list": []
		}
	}
}